skaida/__init__.py
skaida/skaida.py
skaida-1.1.5.dist-info/LICENSE.txt
skaida-1.1.5.dist-info/METADATA
skaida-1.1.5.dist-info/WHEEL
skaida-1.1.5.dist-info/entry_points.txt
skaida-1.1.5.dist-info/top_level.txt
skaida-1.1.5.dist-info/RECORD
